{"cameraMode":{"drawMode":0,"name":"Shaded","section":"Shading Mode"},"sceneLighting":true,"audioPlay":false,"sceneViewState":{"showFog":true,"showMaterialUpdate":false,"showSkybox":true,"showFlares":true,"showImageEffects":true,"showParticleSystems":true},"in2DMode":false,"pivot":{"x":2.1325464248657228,"y":1.183025598526001,"z":8.622902870178223},"rotation":{"x":-0.3487040102481842,"y":-0.49933770298957827,"z":0.22930335998535157,"w":-0.7592962980270386},"size":4.158590316772461,"orthographic":false}